pyannote_viewer/__init__.py
pyannote_viewer/pyannote_viewer.py
pyannote_viewer/pyannote_viewer.pyi
pyannote_viewer/templates/component/__vite-browser-external-2447137e.js
pyannote_viewer/templates/component/index.js
pyannote_viewer/templates/component/module-2c3384e6.js
pyannote_viewer/templates/component/module-5eba924d.js
pyannote_viewer/templates/component/module-a5e22de5.js
pyannote_viewer/templates/component/style.css
pyannote_viewer/templates/component/wrapper-6f348d45-19fa94bf.js
pyannote_viewer/templates/example/index.js
pyannote_viewer/templates/example/style.css
pyannote_viewer-1.0.2.dist-info/METADATA
pyannote_viewer-1.0.2.dist-info/WHEEL
pyannote_viewer-1.0.2.dist-info/RECORD
