Metadata-Version: 2.4
Name: pyannote_viewer
Version: 1.0.2
Summary: Gradio custom component to visualize pyannote's pipelines outputs
Author-email: Clément Pagés <clement.pages@irit.fr>
License-Expression: MIT
Keywords: gradio-custom-component,gradio-template-Audio,pixit,pyannote-audio,source-separation,speaker,speaker-diarization,speech,speech-separation,totatonet,voice-activity-detection
Classifier: Development Status :: 3 - Alpha
Classifier: License :: OSI Approved :: MIT License
Classifier: Operating System :: OS Independent
Classifier: Programming Language :: Python :: 3
Classifier: Programming Language :: Python :: 3 :: Only
Classifier: Programming Language :: Python :: 3.10
Classifier: Programming Language :: Python :: 3.11
Classifier: Topic :: Scientific/Engineering
Classifier: Topic :: Scientific/Engineering :: Artificial Intelligence
Classifier: Topic :: Scientific/Engineering :: Visualization
Requires-Python: >=3.10
Requires-Dist: gradio<5.0,>=4.0
Provides-Extra: dev
Requires-Dist: build; extra == 'dev'
Requires-Dist: twine; extra == 'dev'
